odoo/addons/l10n_cl_etd_stock/README.rst
odoo/addons/l10n_cl_etd_stock/__init__.py
odoo/addons/l10n_cl_etd_stock/__manifest__.py
odoo/addons/l10n_cl_etd_stock/data/etd_document.xml
odoo/addons/l10n_cl_etd_stock/data/etd_document_file.xml
odoo/addons/l10n_cl_etd_stock/i18n/es_CL.po
odoo/addons/l10n_cl_etd_stock/i18n/l10n_cl_etd_stock.pot
odoo/addons/l10n_cl_etd_stock/models/__init__.py
odoo/addons/l10n_cl_etd_stock/models/delivery_carrier.py
odoo/addons/l10n_cl_etd_stock/models/etd_document.py
odoo/addons/l10n_cl_etd_stock/models/stock_picking.py
odoo/addons/l10n_cl_etd_stock/models/stock_picking_batch.py
odoo/addons/l10n_cl_etd_stock/readme/CONFIGURE.rst
odoo/addons/l10n_cl_etd_stock/readme/CONTRIBUTORS.rst
odoo/addons/l10n_cl_etd_stock/readme/DESCRIPTION.rst
odoo/addons/l10n_cl_etd_stock/readme/USAGE.rst
odoo/addons/l10n_cl_etd_stock/static/description/icon.png
odoo/addons/l10n_cl_etd_stock/static/description/index.html
odoo/addons/l10n_cl_etd_stock/static/xml/picking.xml
odoo/addons/l10n_cl_etd_stock/static/xsd/DTE_v10.xsd
odoo/addons/l10n_cl_etd_stock/views/delivery_carrier.xml
odoo/addons/l10n_cl_etd_stock/views/stock_picking.xml
odoo/addons/l10n_cl_etd_stock/views/stock_picking_batch.xml
odoo12_addon_l10n_cl_etd_stock-12.0.1.2.0.dist-info/METADATA
odoo12_addon_l10n_cl_etd_stock-12.0.1.2.0.dist-info/WHEEL
odoo12_addon_l10n_cl_etd_stock-12.0.1.2.0.dist-info/top_level.txt
odoo12_addon_l10n_cl_etd_stock-12.0.1.2.0.dist-info/RECORD
